qinglong_sdk/__init__.py
qinglong_sdk/ql_sdk.py
qinglong_app_sdk-0.1.0.6.dist-info/METADATA
qinglong_app_sdk-0.1.0.6.dist-info/WHEEL
qinglong_app_sdk-0.1.0.6.dist-info/top_level.txt
qinglong_app_sdk-0.1.0.6.dist-info/RECORD
